main.py
copyclipboard-0.1.0.dist-info/METADATA
copyclipboard-0.1.0.dist-info/WHEEL
copyclipboard-0.1.0.dist-info/entry_points.txt
copyclipboard-0.1.0.dist-info/top_level.txt
copyclipboard-0.1.0.dist-info/RECORD
