Metadata-Version: 2.1
Name: copyclipboard
Version: 0.1.0
Summary: A tool to copy folder structures and file contents to clipboard.
Home-page: https://github.com/amirarsalan90/copyclipboard
Author: Amirarsalan Rajabi
Classifier: Programming Language :: Python :: 3
Classifier: License :: OSI Approved :: MIT License
Classifier: Operating System :: OS Independent
Requires-Python: >=3.6
Requires-Dist: pyperclip
